README.rst
setup.cfg
setup.py
src/pytest_helper/__init__.py
src/pytest_helper/config_file_handler.py
src/pytest_helper/global_settings.py
src/pytest_helper/pytest_helper_main.py
src/pytest_helper.egg-info/PKG-INFO
src/pytest_helper.egg-info/SOURCES.txt
src/pytest_helper.egg-info/dependency_links.txt
src/pytest_helper.egg-info/not-zip-safe
src/pytest_helper.egg-info/requires.txt
src/pytest_helper.egg-info/top_level.txt
test/test_intro_example.py
test/test_locals_to_globals.py
test/test_pytest_helper.py