Metadata-Version: 1.1
Name: pytest-helper
Version: 0.2.2
Summary: Functions to help in using the pytest testing framework
Home-page: https://github.com/abarker/pytest-helper
Author: Allen Barker
Author-email: Allen.L.Barker@gmail.com
License: MIT
Keywords: pytest,py.test,unit tests,testing,running tests
Platform: UNKNOWN
Classifier: Development Status :: 5 - Production/Stable
Classifier: Intended Audience :: Developers
Classifier: License :: OSI Approved :: MIT License
Classifier: Operating System :: Unix
Classifier: Operating System :: POSIX
Classifier: Operating System :: Microsoft :: Windows
Classifier: Programming Language :: Python
Classifier: Programming Language :: Python :: 2.7
Classifier: Programming Language :: Python :: 3
Classifier: Programming Language :: Python :: 3.3
Classifier: Programming Language :: Python :: 3.4
Classifier: Programming Language :: Python :: 3.5
Classifier: Programming Language :: Python :: Implementation :: CPython
Classifier: Programming Language :: Python :: Implementation :: PyPy
Classifier: Topic :: Utilities
